FPGA_Version/i2c_master.v
`timescale 1ns/1ns

module i2c_master (
    input wire clk,
    input wire reset,
    input wire start,
    input wire [6:0] addr,  // Slave Address
    input wire [7:0] data,  // Data to write
    input wire sda,         // Bidirectional data line
    output wire scl,        // Clock line
    output reg busy,        // 1 if transaction in prog
    output reg ack_error    // 1 if sensor unresponsive
);

    // Tristate bufer
    reg sda_out;
    reg sda_en;

    assign sda = (sda_en && sda_out == 0) ? 1'b0:1'bz;

    // Timing generator
    reg [4:0] clk_count;
    reg i2c_tick;

    // 12MHz/30 = 400kHz
    always @(posedge clk) begin
        if (reset) begin
            clk_count <= 0;
            i2c_tick <= 0;
        end else if (clk_count == 29) begin
            clk_count <= 0;
            i2c_tick <= 1;
        end else begin
            clk_count <= clk_count + 1;
            i2c_tick <= 0;
        end
    end

    // State machine
    localparam IDLE = 0, START = 1, ADDR = 2, WAIT_ACK1 = 3,
    DATA = 4, WAIT_ACK2 = 5, STOP = 6;

    reg [2:0] state;
    reg [2:0] bit_count;
    reg [1:0] substate;
    reg scl_reg;

    assign scl = scl_reg;

    always @(posedge clk) begin
        if (reset) begin
            state <= IDLE;
            scl_reg <= 1;
            sda_en <= 0; sda_out <= 1;
            busy <= 0;
            ack_error <= 0;
            substate <= 0;
        end else if (i2c_tick) begin
            case (state)
                IDLE: begin
                    scl_reg <= 1; sda_en <= 0; busy <= 0;
                    if (start) begin
                        state <= START;
                        substate <= 0;
                        busy <= 1;
                        ack_error <= 0;
                        bit_count <= 6; // Sending 7-bit addr
                    end
                end

                START: begin
                    // Substate 0: (Setup) SDA High, SCL High
                    if (substate == 0) begin sda_en <= 1; sda_out <= 1; scl_reg <= 1; end
                    // Substate 1: (Start Condition) SDA drops low
                    if (substate == 1) begin sda_en <= 1; sda_out <= 0; end
                    // Substate 3: (Prep for Addr) SCL drops low
                    if (substate == 2) begin scl_reg <= 0; state <= ADDR; end
                    substate <= substate + 1;
                end

                ADDR: begin
                    // SCL Pulse
                    scl_reg <= (substate == 1 || substate == 2);
                    // Change data when SCL is low (Substate 0)
                    if (substate == 0) begin
                        sda_en <= 1;
                        sda_out <= addr[bit_count];
                    end

                    if (substate == 3) begin
                        if (bit_count == 0) begin
                            state <= WAIT_ACK1;
                        end else begin
                            bit_count <= bit_count - 1;
                        end
                    end
                    substate <= substate + 1;
                end

                WAIT_ACK1: begin
                    scl_reg <= (substate == 1 || substate == 2);
                    // Release SDA so slave can pull it low
                    if (substate == 0) sda_en <= 0;
                    // Sample SDA in middle of high SCL (Substate 2)
                    if (substate == 2) begin
                        if (sda == 1) ack_error <= 1;
                    end

                    if (substate == 3) begin
                        state <= DATA;
                        bit_count <= 7;
                    end
                    substate <= substate + 1;
                end

                DATA: begin
                    scl_reg <= (substate == 1 || substate == 2);
                    if (substate == 0) begin
                        sda_en <= 1;
                        sda_out <= data[bit_count];
                    end

                    if (substate == 3) begin
                        if (bit_count == 0) state <= WAIT_ACK2;
                        else bit_count <= bit_count - 1;
                    end
                    substate <= substate + 1;
                end 
                
                WAIT_ACK2: begin
                    scl_reg <= (substate == 1 || substate == 2);
                    if (substate == 0) sda_en <= 0;
                    if (substate == 2) begin
                        if (sda == 1) ack_error <= 1;
                    end
                    if (substate == 3) state <= STOP;
                    substate <= substate + 1;
                end

                STOP: begin
                    if (substate == 0) begin sda_en <= 1; sda_out <= 0; scl_reg <= 0; end
                    if (substate == 1) scl_reg <= 1; // SCL High
                    if (substate == 2) sda_out <= 1; // SDA rises while SCL is High
                    if (substate == 3) state <= IDLE;
                    substate <= substate + 1;
                end
            endcase
        end
    end
endmodule

FPGA_Version/i2c_master_tb.v
`timescale 1ns/1ns

module i2c_tb;
    reg clk;
    reg reset;
    reg start;
    reg [6:0] addr;
    reg [7:0] data;
    wire sda;
    wire scl;
    wire busy;
    wire ack_error;

    i2c_master uut (
        .clk(clk),
        .reset(reset),
        .start(start),
        .addr(addr),
        .data(data),
        .sda(sda),
        .scl(scl),
        .busy(busy),
        .ack_error(ack_error)
    );

    initial begin
        clk = 0;
        forever #41.66 clk = ~clk;
    end

    pullup(sda);
    pullup(scl);

    reg slave_drive_ack;

    assign sda = (slave_drive_ack) ? 1'b0 : 1'bz;

    
    initial begin
        // Init: Sensor asleep
        slave_drive_ack = 0;
        // Wait until master
        wait(start == 1);
        
        // Address ack
        #90000;
        // Wait for falling edge
        @(negedge scl);
        slave_drive_ack = 1;
        // Hold one clk cycle
        @(negedge scl);
        slave_drive_ack = 0;

        // Data ack
        #90000;
        @(negedge scl);
        slave_drive_ack = 1;
        @(negedge scl)
        slave_drive_ack = 0;
    end

    initial begin
        $dumpfile("i2c_tb.vcd");
        $dumpvars(0, i2c_tb);

        // Init inputs
        reset = 1;
        start = 0;
        addr = 7'h59;   // Address of SGP40 sensor
        data = 8'h6A;   // Random test data

        // Sequence
        #200 reset = 0;       // Release reset
        #1000 start = 1;    // Press start
        #5000 start = 0;     // Release start
        wait(busy == 1);
        // Wait for master to finish
        wait(busy == 0);

        #5000;
        $finish;
    end
endmodule

FPGA_Version/i2c_tb.vcd
$date
	Fri Nov 28 00:18:06 2025
$end
$version
	Icarus Verilog
$end
$timescale
	1ns
$end
$scope module i2c_tb $end
$var wire 1 ! scl $end
$var wire 1 " sda $end
$var wire 1 # busy $end
$var wire 1 $ ack_error $end
$var reg 7 % addr [6:0] $end
$var reg 1 & clk $end
$var reg 8 ' data [7:0] $end
$var reg 1 ( reset $end
$var reg 1 ) slave_drive_ack $end
$var reg 1 * start $end
$scope module uut $end
$var wire 7 + addr [6:0] $end
$var wire 1 & clk $end
$var wire 8 , data [7:0] $end
$var wire 1 ( reset $end
$var wire 1 ! scl $end
$var wire 1 " sda $end
$var wire 1 * start $end
$var parameter 32 - ADDR $end
$var parameter 32 . DATA $end
$var parameter 32 / IDLE $end
$var parameter 32 0 START $end
$var parameter 32 1 STOP $end
$var parameter 32 2 WAIT_ACK1 $end
$var parameter 32 3 WAIT_ACK2 $end
$var reg 1 $ ack_error $end
$var reg 3 4 bit_count [2:0] $end
$var reg 1 # busy $end
$var reg 5 5 clk_count [4:0] $end
$var reg 1 6 i2c_tick $end
$var reg 1 7 scl_reg $end
$var reg 1 8 sda_en $end
$var reg 1 9 sda_out $end
$var reg 3 : state [2:0] $end
$var reg 2 ; substate [1:0] $end
$upscope $end
$upscope $end
$enddefinitions $end
$comment Show the parameter values. $end
$dumpall
b101 3
b11 2
b110 1
b1 0
b0 /
b100 .
b10 -
$end
#0
$dumpvars
bx ;
bx :
x9
x8
x7
x6
bx 5
bx 4
b1101010 ,
b1011001 +
0*
0)
1(
b1101010 '
0&
b1011001 %
x$
x#
x"
x!
$end
#42
1"
06
b0 5
b0 ;
0$
0#
19
08
1!
17
b0 :
1&
#84
0&
#126
1&
#168
0&
#200
0(
#210
b1 5
1&
#252
0&
#294
b10 5
1&
#336
0&
#378
b11 5
1&
#420
0&
#462
b100 5
1&
#504
0&
#546
b101 5
1&
#588
0&
#630
b110 5
1&
#672
0&
#714
b111 5
1&
#756
0&
#798
b1000 5
1&
#840
0&
#882
b1001 5
1&
#924
0&
#966
b1010 5
1&
#1008
0&
#1050
b1011 5
1&
#1092
0&
#1134
b1100 5
1&
#1176
0&
#1200
1*
#1218
b1101 5
1&
#1260
0&
#1302
b1110 5
1&
#1344
0&
#1386
b1111 5
1&
#1428
0&
#1470
b10000 5
1&
#1512
0&
#1554
b10001 5
1&
#1596
0&
#1638
b10010 5
1&
#1680
0&
#1722
b10011 5
1&
#1764
0&
#1806
b10100 5
1&
#1848
0&
#1890
b10101 5
1&
#1932
0&
#1974
b10110 5
1&
#2016
0&
#2058
b10111 5
1&
#2100
0&
#2142
b11000 5
1&
#2184
0&
#2226
b11001 5
1&
#2268
0&
#2310
b11010 5
1&
#2352
0&
#2394
b11011 5
1&
#2436
0&
#2478
b11100 5
1&
#2520
0&
#2562
b11101 5
1&
#2604
0&
#2646
16
b0 5
1&
#2688
0&
#2730
06
b1 5
b110 4
1#
b1 :
1&
#2772
0&
#2814
b10 5
1&
#2856
0&
#2898
b11 5
1&
#2940
0&
#2982
b100 5
1&
#3024
0&
#3066
b101 5
1&
#3108
0&
#3150
b110 5
1&
#3192
0&
#3234
b111 5
1&
#3276
0&
#3318
b1000 5
1&
#3360
0&
#3402
b1001 5
1&
#3444
0&
#3486
b1010 5
1&
#3528
0&
#3570
b1011 5
1&
#3612
0&
#3654
b1100 5
1&
#3696
0&
#3738
b1101 5
1&
#3780
0&
#3822
b1110 5
1&
#3864
0&
#3906
b1111 5
1&
#3948
0&
#3990
b10000 5
1&
#4032
0&
#4074
b10001 5
1&
#4116
0&
#4158
b10010 5
1&
#4200
0&
#4242
b10011 5
1&
#4284
0&
#4326
b10100 5
1&
#4368
0&
#4410
b10101 5
1&
#4452
0&
#4494
b10110 5
1&
#4536
0&
#4578
b10111 5
1&
#4620
0&
#4662
b11000 5
1&
#4704
0&
#4746
b11001 5
1&
#4788
0&
#4830
b11010 5
1&
#4872
0&
#4914
b11011 5
1&
#4956
0&
#4998
b11100 5
1&
#5040
0&
#5082
b11101 5
1&
#5124
0&
#5166
16
b0 5
1&
#5208
0&
#5250
06
b1 5
b1 ;
18
1&
#5292
0&
#5334
b10 5
1&
#5376
0&
#5418
b11 5
1&
#5460
0&
#5502
b100 5
1&
#5544
0&
#5586
b101 5
1&
#5628
0&
#5670
b110 5
1&
#5712
0&
#5754
b111 5
1&
#5796
0&
#5838
b1000 5
1&
#5880
0&
#5922
b1001 5
1&
#5964
0&
#6006
b1010 5
1&
#6048
0&
#6090
b1011 5
1&
#6132
0&
#6174
b1100 5
1&
#6200
0*
#6216
0&
#6258
b1101 5
1&
#6300
0&
#6342
b1110 5
1&
#6384
0&
#6426
b1111 5
1&
#6468
0&
#6510
b10000 5
1&
#6552
0&
#6594
b10001 5
1&
#6636
0&
#6678
b10010 5
1&
#6720
0&
#6762
b10011 5
1&
#6804
0&
#6846
b10100 5
1&
#6888
0&
#6930
b10101 5
1&
#6972
0&
#7014
b10110 5
1&
#7056
0&
#7098
b10111 5
1&
#7140
0&
#7182
b11000 5
1&
#7224
0&
#7266
b11001 5
1&
#7308
0&
#7350
b11010 5
1&
#7392
0&
#7434
b11011 5
1&
#7476
0&
#7518
b11100 5
1&
#7560
0&
#7602
b11101 5
1&
#7644
0&
#7686
16
b0 5
1&
#7728
0&
#7770
0"
06
b1 5
b10 ;
09
1&
#7812
0&
#7854
b10 5
1&
#7896
0&
#7938
b11 5
1&
#7980
0&
#8022
b100 5
1&
#8064
0&
#8106
b101 5
1&
#8148
0&
#8190
b110 5
1&
#8232
0&
#8274
b111 5
1&
#8316
0&
#8358
b1000 5
1&
#8400
0&
#8442
b1001 5
1&
#8484
0&
#8526
b1010 5
1&
#8568
0&
#8610
b1011 5
1&
#8652
0&
#8694
b1100 5
1&
#8736
0&
#8778
b1101 5
1&
#8820
0&
#8862
b1110 5
1&
#8904
0&
#8946
b1111 5
1&
#8988
0&
#9030
b10000 5
1&
#9072
0&
#9114
b10001 5
1&
#9156
0&
#9198
b10010 5
1&
#9240
0&
#9282
b10011 5
1&
#9324
0&
#9366
b10100 5
1&
#9408
0&
#9450
b10101 5
1&
#9492
0&
#9534
b10110 5
1&
#9576
0&
#9618
b10111 5
1&
#9660
0&
#9702
b11000 5
1&
#9744
0&
#9786
b11001 5
1&
#9828
0&
#9870
b11010 5
1&
#9912
0&
#9954
b11011 5
1&
#9996
0&
#10038
b11100 5
1&
#10080
0&
#10122
b11101 5
1&
#10164
0&
#10206
16
b0 5
1&
#10248
0&
#10290
06
b1 5
b11 ;
b10 :
0!
07
1&
#10332
0&
#10374
b10 5
1&
#10416
0&
#10458
b11 5
1&
#10500
0&
#10542
b100 5
1&
#10584
0&
#10626
b101 5
1&
#10668
0&
#10710
b110 5
1&
#10752
0&
#10794
b111 5
1&
#10836
0&
#10878
b1000 5
1&
#10920
0&
#10962
b1001 5
1&
#11004
0&
#11046
b1010 5
1&
#11088
0&
#11130
b1011 5
1&
#11172
0&
#11214
b1100 5
1&
#11256
0&
#11298
b1101 5
1&
#11340
0&
#11382
b1110 5
1&
#11424
0&
#11466
b1111 5
1&
#11508
0&
#11550
b10000 5
1&
#11592
0&
#11634
b10001 5
1&
#11676
0&
#11718
b10010 5
1&
#11760
0&
#11802
b10011 5
1&
#11844
0&
#11886
b10100 5
1&
#11928
0&
#11970
b10101 5
1&
#12012
0&
#12054
b10110 5
1&
#12096
0&
#12138
b10111 5
1&
#12180
0&
#12222
b11000 5
1&
#12264
0&
#12306
b11001 5
1&
#12348
0&
#12390
b11010 5
1&
#12432
0&
#12474
b11011 5
1&
#12516
0&
#12558
b11100 5
1&
#12600
0&
#12642
b11101 5
1&
#12684
0&
#12726
16
b0 5
1&
#12768
0&
#12810
06
b1 5
b0 ;
b101 4
1&
#12852
0&
#12894
b10 5
1&
#12936
0&
#12978
b11 5
1&
#13020
0&
#13062
b100 5
1&
#13104
0&
#13146
b101 5
1&
#13188
0&
#13230
b110 5
1&
#13272
0&
#13314
b111 5
1&
#13356
0&
#13398
b1000 5
1&
#13440
0&
#13482
b1001 5
1&
#13524
0&
#13566
b1010 5
1&
#13608
0&
#13650
b1011 5
1&
#13692
0&
#13734
b1100 5
1&
#13776
0&
#13818
b1101 5
1&
#13860
0&
#13902
b1110 5
1&
#13944
0&
#13986
b1111 5
1&
#14028
0&
#14070
b10000 5
1&
#14112
0&
#14154
b10001 5
1&
#14196
0&
#14238
b10010 5
1&
#14280
0&
#14322
b10011 5
1&
#14364
0&
#14406
b10100 5
1&
#14448
0&
#14490
b10101 5
1&
#14532
0&
#14574
b10110 5
1&
#14616
0&
#14658
b10111 5
1&
#14700
0&
#14742
b11000 5
1&
#14784
0&
#14826
b11001 5
1&
#14868
0&
#14910
b11010 5
1&
#14952
0&
#14994
b11011 5
1&
#15036
0&
#15078
b11100 5
1&
#15120
0&
#15162
b11101 5
1&
#15204
0&
#15246
16
b0 5
1&
#15288
0&
#15330
06
b1 5
b1 ;
1&
#15372
0&
#15414
b10 5
1&
#15456
0&
#15498
b11 5
1&
#15540
0&
#15582
b100 5
1&
#15624
0&
#15666
b101 5
1&
#15708
0&
#15750
b110 5
1&
#15792
0&
#15834
b111 5
1&
#15876
0&
#15918
b1000 5
1&
#15960
0&
#16002
b1001 5
1&
#16044
0&
#16086
b1010 5
1&
#16128
0&
#16170
b1011 5
1&
#16212
0&
#16254
b1100 5
1&
#16296
0&
#16338
b1101 5
1&
#16380
0&
#16422
b1110 5
1&
#16464
0&
#16506
b1111 5
1&
#16548
0&
#16590
b10000 5
1&
#16632
0&
#16674
b10001 5
1&
#16716
0&
#16758
b10010 5
1&
#16800
0&
#16842
b10011 5
1&
#16884
0&
#16926
b10100 5
1&
#16968
0&
#17010
b10101 5
1&
#17052
0&
#17094
b10110 5
1&
#17136
0&
#17178
b10111 5
1&
#17220
0&
#17262
b11000 5
1&
#17304
0&
#17346
b11001 5
1&
#17388
0&
#17430
b11010 5
1&
#17472
0&
#17514
b11011 5
1&
#17556
0&
#17598
b11100 5
1&
#17640
0&
#17682
b11101 5
1&
#17724
0&
#17766
16
b0 5
1&
#17808
0&
#17850
06
b1 5
b10 ;
1!
17
1&
#17892
0&
#17934
b10 5
1&
#17976
0&
#18018
b11 5
1&
#18060
0&
#18102
b100 5
1&
#18144
0&
#18186
b101 5
1&
#18228
0&
#18270
b110 5
1&
#18312
0&
#18354
b111 5
1&
#18396
0&
#18438
b1000 5
1&
#18480
0&
#18522
b1001 5
1&
#18564
0&
#18606
b1010 5
1&
#18648
0&
#18690
b1011 5
1&
#18732
0&
#18774
b1100 5
1&
#18816
0&
#18858
b1101 5
1&
#18900
0&
#18942
b1110 5
1&
#18984
0&
#19026
b1111 5
1&
#19068
0&
#19110
b10000 5
1&
#19152
0&
#19194
b10001 5
1&
#19236
0&
#19278
b10010 5
1&
#19320
0&
#19362
b10011 5
1&
#19404
0&
#19446
b10100 5
1&
#19488
0&
#19530
b10101 5
1&
#19572
0&
#19614
b10110 5
1&
#19656
0&
#19698
b10111 5
1&
#19740
0&
#19782
b11000 5
1&
#19824
0&
#19866
b11001 5
1&
#19908
0&
#19950
b11010 5
1&
#19992
0&
#20034
b11011 5
1&
#20076
0&
#20118
b11100 5
1&
#20160
0&
#20202
b11101 5
1&
#20244
0&
#20286
16
b0 5
1&
#20328
0&
#20370
06
b1 5
b11 ;
1&
#20412
0&
#20454
b10 5
1&
#20496
0&
#20538
b11 5
1&
#20580
0&
#20622
b100 5
1&
#20664
0&
#20706
b101 5
1&
#20748
0&
#20790
b110 5
1&
#20832
0&
#20874
b111 5
1&
#20916
0&
#20958
b1000 5
1&
#21000
0&
#21042
b1001 5
1&
#21084
0&
#21126
b1010 5
1&
#21168
0&
#21210
b1011 5
1&
#21252
0&
#21294
b1100 5
1&
#21336
0&
#21378
b1101 5
1&
#21420
0&
#21462
b1110 5
1&
#21504
0&
#21546
b1111 5
1&
#21588
0&
#21630
b10000 5
1&
#21672
0&
#21714
b10001 5
1&
#21756
0&
#21798
b10010 5
1&
#21840
0&
#21882
b10011 5
1&
#21924
0&
#21966
b10100 5
1&
#22008
0&
#22050
b10101 5
1&
#22092
0&
#22134
b10110 5
1&
#22176
0&
#22218
b10111 5
1&
#22260
0&
#22302
b11000 5
1&
#22344
0&
#22386
b11001 5
1&
#22428
0&
#22470
b11010 5
1&
#22512
0&
#22554
b11011 5
1&
#22596
0&
#22638
b11100 5
1&
#22680
0&
#22722
b11101 5
1&
#22764
0&
#22806
16
b0 5
1&
#22848
0&
#22890
06
b1 5
b0 ;
b100 4
0!
07
1&
#22932
0&
#22974
b10 5
1&
#23016
0&
#23058
b11 5
1&
#23100
0&
#23142
b100 5
1&
#23184
0&
#23226
b101 5
1&
#23268
0&
#23310
b110 5
1&
#23352
0&
#23394
b111 5
1&
#23436
0&
#23478
b1000 5
1&
#23520
0&
#23562
b1001 5
1&
#23604
0&
#23646
b1010 5
1&
#23688
0&
#23730
b1011 5
1&
#23772
0&
#23814
b1100 5
1&
#23856
0&
#23898
b1101 5
1&
#23940
0&
#23982
b1110 5
1&
#24024
0&
#24066
b1111 5
1&
#24108
0&
#24150
b10000 5
1&
#24192
0&
#24234
b10001 5
1&
#24276
0&
#24318
b10010 5
1&
#24360
0&
#24402
b10011 5
1&
#24444
0&
#24486
b10100 5
1&
#24528
0&
#24570
b10101 5
1&
#24612
0&
#24654
b10110 5
1&
#24696
0&
#24738
b10111 5
1&
#24780
0&
#24822
b11000 5
1&
#24864
0&
#24906
b11001 5
1&
#24948
0&
#24990
b11010 5
1&
#25032
0&
#25074
b11011 5
1&
#25116
0&
#25158
b11100 5
1&
#25200
0&
#25242
b11101 5
1&
#25284
0&
#25326
16
b0 5
1&
#25368
0&
#25410
1"
06
b1 5
b1 ;
19
1&
#25452
0&
#25494
b10 5
1&
#25536
0&
#25578
b11 5
1&
#25620
0&
#25662
b100 5
1&
#25704
0&
#25746
b101 5
1&
#25788
0&
#25830
b110 5
1&
#25872
0&
#25914
b111 5
1&
#25956
0&
#25998
b1000 5
1&
#26040
0&
#26082
b1001 5
1&
#26124
0&
#26166
b1010 5
1&
#26208
0&
#26250
b1011 5
1&
#26292
0&
#26334
b1100 5
1&
#26376
0&
#26418
b1101 5
1&
#26460
0&
#26502
b1110 5
1&
#26544
0&
#26586
b1111 5
1&
#26628
0&
#26670
b10000 5
1&
#26712
0&
#26754
b10001 5
1&
#26796
0&
#26838
b10010 5
1&
#26880
0&
#26922
b10011 5
1&
#26964
0&
#27006
b10100 5
1&
#27048
0&
#27090
b10101 5
1&
#27132
0&
#27174
b10110 5
1&
#27216
0&
#27258
b10111 5
1&
#27300
0&
#27342
b11000 5
1&
#27384
0&
#27426
b11001 5
1&
#27468
0&
#27510
b11010 5
1&
#27552
0&
#27594
b11011 5
1&
#27636
0&
#27678
b11100 5
1&
#27720
0&
#27762
b11101 5
1&
#27804
0&
#27846
16
b0 5
1&
#27888
0&
#27930
06
b1 5
b10 ;
1!
17
1&
#27972
0&
#28014
b10 5
1&
#28056
0&
#28098
b11 5
1&
#28140
0&
#28182
b100 5
1&
#28224
0&
#28266
b101 5
1&
#28308
0&
#28350
b110 5
1&
#28392
0&
#28434
b111 5
1&
#28476
0&
#28518
b1000 5
1&
#28560
0&
#28602
b1001 5
1&
#28644
0&
#28686
b1010 5
1&
#28728
0&
#28770
b1011 5
1&
#28812
0&
#28854
b1100 5
1&
#28896
0&
#28938
b1101 5
1&
#28980
0&
#29022
b1110 5
1&
#29064
0&
#29106
b1111 5
1&
#29148
0&
#29190
b10000 5
1&
#29232
0&
#29274
b10001 5
1&
#29316
0&
#29358
b10010 5
1&
#29400
0&
#29442
b10011 5
1&
#29484
0&
#29526
b10100 5
1&
#29568
0&
#29610
b10101 5
1&
#29652
0&
#29694
b10110 5
1&
#29736
0&
#29778
b10111 5
1&
#29820
0&
#29862
b11000 5
1&
#29904
0&
#29946
b11001 5
1&
#29988
0&
#30030
b11010 5
1&
#30072
0&
#30114
b11011 5
1&
#30156
0&
#30198
b11100 5
1&
#30240
0&
#30282
b11101 5
1&
#30324
0&
#30366
16
b0 5
1&
#30408
0&
#30450
06
b1 5
b11 ;
1&
#30492
0&
#30534
b10 5
1&
#30576
0&
#30618
b11 5
1&
#30660
0&
#30702
b100 5
1&
#30744
0&
#30786
b101 5
1&
#30828
0&
#30870
b110 5
1&
#30912
0&
#30954
b111 5
1&
#30996
0&
#31038
b1000 5
1&
#31080
0&
#31122
b1001 5
1&
#31164
0&
#31206
b1010 5
1&
#31248
0&
#31290
b1011 5
1&
#31332
0&
#31374
b1100 5
1&
#31416
0&
#31458
b1101 5
1&
#31500
0&
#31542
b1110 5
1&
#31584
0&
#31626
b1111 5
1&
#31668
0&
#31710
b10000 5
1&
#31752
0&
#31794
b10001 5
1&
#31836
0&
#31878
b10010 5
1&
#31920
0&
#31962
b10011 5
1&
#32004
0&
#32046
b10100 5
1&
#32088
0&
#32130
b10101 5
1&
#32172
0&
#32214
b10110 5
1&
#32256
0&
#32298
b10111 5
1&
#32340
0&
#32382
b11000 5
1&
#32424
0&
#32466
b11001 5
1&
#32508
0&
#32550
b11010 5
1&
#32592
0&
#32634
b11011 5
1&
#32676
0&
#32718
b11100 5
1&
#32760
0&
#32802
b11101 5
1&
#32844
0&
#32886
16
b0 5
1&
#32928
0&
#32970
06
b1 5
b0 ;
b11 4
0!
07
1&
#33012
0&
#33054
b10 5
1&
#33096
0&
#33138
b11 5
1&
#33180
0&
#33222
b100 5
1&
#33264
0&
#33306
b101 5
1&
#33348
0&
#33390
b110 5
1&
#33432
0&
#33474
b111 5
1&
#33516
0&
#33558
b1000 5
1&
#33600
0&
#33642
b1001 5
1&
#33684
0&
#33726
b1010 5
1&
#33768
0&
#33810
b1011 5
1&
#33852
0&
#33894
b1100 5
1&
#33936
0&
#33978
b1101 5
1&
#34020
0&
#34062
b1110 5
1&
#34104
0&
#34146
b1111 5
1&
#34188
0&
#34230
b10000 5
1&
#34272
0&
#34314
b10001 5
1&
#34356
0&
#34398
b10010 5
1&
#34440
0&
#34482
b10011 5
1&
#34524
0&
#34566
b10100 5
1&
#34608
0&
#34650
b10101 5
1&
#34692
0&
#34734
b10110 5
1&
#34776
0&
#34818
b10111 5
1&
#34860
0&
#34902
b11000 5
1&
#34944
0&
#34986
b11001 5
1&
#35028
0&
#35070
b11010 5
1&
#35112
0&
#35154
b11011 5
1&
#35196
0&
#35238
b11100 5
1&
#35280
0&
#35322
b11101 5
1&
#35364
0&
#35406
16
b0 5
1&
#35448
0&
#35490
06
b1 5
b1 ;
1&
#35532
0&
#35574
b10 5
1&
#35616
0&
#35658
b11 5
1&
#35700
0&
#35742
b100 5
1&
#35784
0&
#35826
b101 5
1&
#35868
0&
#35910
b110 5
1&
#35952
0&
#35994
b111 5
1&
#36036
0&
#36078
b1000 5
1&
#36120
0&
#36162
b1001 5
1&
#36204
0&
#36246
b1010 5
1&
#36288
0&
#36330
b1011 5
1&
#36372
0&
#36414
b1100 5
1&
#36456
0&
#36498
b1101 5
1&
#36540
0&
#36582
b1110 5
1&
#36624
0&
#36666
b1111 5
1&
#36708
0&
#36750
b10000 5
1&
#36792
0&
#36834
b10001 5
1&
#36876
0&
#36918
b10010 5
1&
#36960
0&
#37002
b10011 5
1&
#37044
0&
#37086
b10100 5
1&
#37128
0&
#37170
b10101 5
1&
#37212
0&
#37254
b10110 5
1&
#37296
0&
#37338
b10111 5
1&
#37380
0&
#37422
b11000 5
1&
#37464
0&
#37506
b11001 5
1&
#37548
0&
#37590
b11010 5
1&
#37632
0&
#37674
b11011 5
1&
#37716
0&
#37758
b11100 5
1&
#37800
0&
#37842
b11101 5
1&
#37884
0&
#37926
16
b0 5
1&
#37968
0&
#38010
06
b1 5
b10 ;
1!
17
1&
#38052
0&
#38094
b10 5
1&
#38136
0&
#38178
b11 5
1&
#38220
0&
#38262
b100 5
1&
#38304
0&
#38346
b101 5
1&
#38388
0&
#38430
b110 5
1&
#38472
0&
#38514
b111 5
1&
#38556
0&
#38598
b1000 5
1&
#38640
0&
#38682
b1001 5
1&
#38724
0&
#38766
b1010 5
1&
#38808
0&
#38850
b1011 5
1&
#38892
0&
#38934
b1100 5
1&
#38976
0&
#39018
b1101 5
1&
#39060
0&
#39102
b1110 5
1&
#39144
0&
#39186
b1111 5
1&
#39228
0&
#39270
b10000 5
1&
#39312
0&
#39354
b10001 5
1&
#39396
0&
#39438
b10010 5
1&
#39480
0&
#39522
b10011 5
1&
#39564
0&
#39606
b10100 5
1&
#39648
0&
#39690
b10101 5
1&
#39732
0&
#39774
b10110 5
1&
#39816
0&
#39858
b10111 5
1&
#39900
0&
#39942
b11000 5
1&
#39984
0&
#40026
b11001 5
1&
#40068
0&
#40110
b11010 5
1&
#40152
0&
#40194
b11011 5
1&
#40236
0&
#40278
b11100 5
1&
#40320
0&
#40362
b11101 5
1&
#40404
0&
#40446
16
b0 5
1&
#40488
0&
#40530
06
b1 5
b11 ;
1&
#40572
0&
#40614
b10 5
1&
#40656
0&
#40698
b11 5
1&
#40740
0&
#40782
b100 5
1&
#40824
0&
#40866
b101 5
1&
#40908
0&
#40950
b110 5
1&
#40992
0&
#41034
b111 5
1&
#41076
0&
#41118
b1000 5
1&
#41160
0&
#41202
b1001 5
1&
#41244
0&
#41286
b1010 5
1&
#41328
0&
#41370
b1011 5
1&
#41412
0&
#41454
b1100 5
1&
#41496
0&
#41538
b1101 5
1&
#41580
0&
#41622
b1110 5
1&
#41664
0&
#41706
b1111 5
1&
#41748
0&
#41790
b10000 5
1&
#41832
0&
#41874
b10001 5
1&
#41916
0&
#41958
b10010 5
1&
#42000
0&
#42042
b10011 5
1&
#42084
0&
#42126
b10100 5
1&
#42168
0&
#42210
b10101 5
1&
#42252
0&
#42294
b10110 5
1&
#42336
0&
#42378
b10111 5
1&
#42420
0&
#42462
b11000 5
1&
#42504
0&
#42546
b11001 5
1&
#42588
0&
#42630
b11010 5
1&
#42672
0&
#42714
b11011 5
1&
#42756
0&
#42798
b11100 5
1&
#42840
0&
#42882
b11101 5
1&
#42924
0&
#42966
16
b0 5
1&
#43008
0&
#43050
06
b1 5
b0 ;
b10 4
0!
07
1&
#43092
0&
#43134
b10 5
1&
#43176
0&
#43218
b11 5
1&
#43260
0&
#43302
b100 5
1&
#43344
0&
#43386
b101 5
1&
#43428
0&
#43470
b110 5
1&
#43512
0&
#43554
b111 5
1&
#43596
0&
#43638
b1000 5
1&
#43680
0&
#43722
b1001 5
1&
#43764
0&
#43806
b1010 5
1&
#43848
0&
#43890
b1011 5
1&
#43932
0&
#43974
b1100 5
1&
#44016
0&
#44058
b1101 5
1&
#44100
0&
#44142
b1110 5
1&
#44184
0&
#44226
b1111 5
1&
#44268
0&
#44310
b10000 5
1&
#44352
0&
#44394
b10001 5
1&
#44436
0&
#44478
b10010 5
1&
#44520
0&
#44562
b10011 5
1&
#44604
0&
#44646
b10100 5
1&
#44688
0&
#44730
b10101 5
1&
#44772
0&
#44814
b10110 5
1&
#44856
0&
#44898
b10111 5
1&
#44940
0&
#44982
b11000 5
1&
#45024
0&
#45066
b11001 5
1&
#45108
0&
#45150
b11010 5
1&
#45192
0&
#45234
b11011 5
1&
#45276
0&
#45318
b11100 5
1&
#45360
0&
#45402
b11101 5
1&
#45444
0&
#45486
16
b0 5
1&
#45528
0&
#45570
0"
06
b1 5
b1 ;
09
1&
#45612
0&
#45654
b10 5
1&
#45696
0&
#45738
b11 5
1&
#45780
0&
#45822
b100 5
1&
#45864
0&
#45906
b101 5
1&
#45948
0&
#45990
b110 5
1&
#46032
0&
#46074
b111 5
1&
#46116
0&
#46158
b1000 5
1&
#46200
0&
#46242
b1001 5
1&
#46284
0&
#46326
b1010 5
1&
#46368
0&
#46410
b1011 5
1&
#46452
0&
#46494
b1100 5
1&
#46536
0&
#46578
b1101 5
1&
#46620
0&
#46662
b1110 5
1&
#46704
0&
#46746
b1111 5
1&
#46788
0&
#46830
b10000 5
1&
#46872
0&
#46914
b10001 5
1&
#46956
0&
#46998
b10010 5
1&
#47040
0&
#47082
b10011 5
1&
#47124
0&
#47166
b10100 5
1&
#47208
0&
#47250
b10101 5
1&
#47292
0&
#47334
b10110 5
1&
#47376
0&
#47418
b10111 5
1&
#47460
0&
#47502
b11000 5
1&
#47544
0&
#47586
b11001 5
1&
#47628
0&
#47670
b11010 5
1&
#47712
0&
#47754
b11011 5
1&
#47796
0&
#47838
b11100 5
1&
#47880
0&
#47922
b11101 5
1&
#47964
0&
#48006
16
b0 5
1&
#48048
0&
#48090
06
b1 5
b10 ;
1!
17
1&
#48132
0&
#48174
b10 5
1&
#48216
0&
